arekit_ss/__init__.py
arekit_ss/download.py
arekit_ss/download_data.py
arekit_ss/sample.py
arekit_ss/samplers_list.py
arekit_ss/utils.py
arekit_ss/core/__init__.py
arekit_ss/core/rows_bert.py
arekit_ss/core/rows_prompt.py
arekit_ss/core/rows_ru_sentiment_nn.py
arekit_ss/core/samples_io.py
arekit_ss/core/serialize_bert.py
arekit_ss/core/serialize_nn.py
arekit_ss/core/source/__init__.py
arekit_ss/core/source/zip_utils.py
arekit_ss/core/source/brat/__init__.py
arekit_ss/core/source/brat/annot.py
arekit_ss/core/source/brat/doc.py
arekit_ss/core/source/brat/relation.py
arekit_ss/core/source/brat/sentence.py
arekit_ss/core/source/brat/sentences_reader.py
arekit_ss/core/source/brat/entities/__init__.py
arekit_ss/core/source/brat/entities/compound.py
arekit_ss/core/source/brat/entities/entity.py
arekit_ss/core/source/brat/entities/parser.py
arekit_ss/core/source/brat/opinions/__init__.py
arekit_ss/core/source/brat/opinions/converter.py
arekit_ss/core/source/synonyms/__init__.py
arekit_ss/core/source/synonyms/utils.py
arekit_ss/core/utils/__init__.py
arekit_ss/core/utils/download.py
arekit_ss/core/utils/resources.py
arekit_ss/core/utils/lexicons/__init__.py
arekit_ss/core/utils/lexicons/lexicon.py
arekit_ss/core/utils/lexicons/relation.py
arekit_ss/core/utils/lexicons/rusentilex.py
arekit_ss/core/utils/nn/__init__.py
arekit_ss/core/utils/nn/rows.py
arekit_ss/core/utils/vectorizers/__init__.py
arekit_ss/core/utils/vectorizers/base.py
arekit_ss/core/utils/vectorizers/bpe.py
arekit_ss/core/utils/vectorizers/random_norm.py
arekit_ss/entity/__init__.py
arekit_ss/entity/masking.py
arekit_ss/filters/__init__.py
arekit_ss/filters/label_type.py
arekit_ss/filters/object_type.py
arekit_ss/pipelines/__init__.py
arekit_ss/pipelines/annot/__init__.py
arekit_ss/pipelines/annot/predefined.py
arekit_ss/pipelines/text/__init__.py
arekit_ss/pipelines/text/tokenizer.py
arekit_ss/pos/__init__.py
arekit_ss/pos/ru.py
arekit_ss/pos/ru_mystem.py
arekit_ss/sources/__init__.py
arekit_ss-0.25.0.dist-info/LICENSE
arekit_ss-0.25.0.dist-info/METADATA
arekit_ss-0.25.0.dist-info/WHEEL
arekit_ss-0.25.0.dist-info/top_level.txt
arekit_ss-0.25.0.dist-info/RECORD
