Metadata-Version: 2.1
Name: arekit-ss
Version: 0.25.0
Summary: Low Resource Context Relation Sampler for contexts with relations for fact-checking and fine-tuning your LLM models, powered by AREkit
Home-page: https://github.com/nicolay-r/arekit-ss
Author: Nicolay Rusnachenko
Author-email: rusnicolay@gmail.com
License: MIT License
Keywords: relation extraction,data processing
Classifier: Programming Language :: Python
Classifier: Programming Language :: Python :: 3.9
Classifier: Topic :: Scientific/Engineering :: Information Analysis
Classifier: Topic :: Text Processing :: Linguistic
License-File: LICENSE
Requires-Dist: arekit==0.25.0
Requires-Dist: googletrans==3.1.0a0
Requires-Dist: requests>=2.28.1
